flask_limiter/__init__.py
flask_limiter/_compat.py
flask_limiter/_version.py
flask_limiter/commands.py
flask_limiter/constants.py
flask_limiter/errors.py
flask_limiter/extension.py
flask_limiter/manager.py
flask_limiter/py.typed
flask_limiter/typing.py
flask_limiter/util.py
flask_limiter/version.py
flask_limiter/wrappers.py
flask_limiter/contrib/__init__.py
flask_limiter/contrib/util.py
Flask_Limiter-3.10.1.dist-info/LICENSE.txt
Flask_Limiter-3.10.1.dist-info/METADATA
Flask_Limiter-3.10.1.dist-info/WHEEL
Flask_Limiter-3.10.1.dist-info/entry_points.txt
Flask_Limiter-3.10.1.dist-info/top_level.txt
Flask_Limiter-3.10.1.dist-info/RECORD
