Metadata-Version: 2.2
Name: Flask-Limiter
Version: 3.10.1
Summary: Rate limiting for flask applications
Home-page: https://flask-limiter.readthedocs.org
Author: Ali-Akber Saifee
Author-email: ali@indydevs.org
License: MIT
Project-URL: Source, https://github.com/alisaifee/flask-limiter
Classifier: Development Status :: 5 - Production/Stable
Classifier: Environment :: Web Environment
Classifier: Framework :: Flask
Classifier: Intended Audience :: Developers
Classifier: License :: OSI Approved :: MIT License
Classifier: Operating System :: MacOS
Classifier: Operating System :: POSIX :: Linux
Classifier: Operating System :: OS Independent
Classifier: Topic :: Software Development :: Libraries :: Python Modules
Classifier: Programming Language :: Python :: 3.9
Classifier: Programming Language :: Python :: 3.10
Classifier: Programming Language :: Python :: 3.11
Classifier: Programming Language :: Python :: 3.12
Classifier: Programming Language :: Python :: 3.13
Requires-Python: >=3.9
License-File: LICENSE.txt
Requires-Dist: limits>=3.13
Requires-Dist: Flask>=2
Requires-Dist: ordered-set<5,>4
Requires-Dist: rich<14,>=12
Requires-Dist: typing_extensions>=4
Provides-Extra: redis
Requires-Dist: limits[redis]; extra == "redis"
Provides-Extra: memcached
Requires-Dist: limits[memcached]; extra == "memcached"
Provides-Extra: mongodb
Requires-Dist: limits[mongodb]; extra == "mongodb"
Dynamic: author
Dynamic: author-email
Dynamic: classifier
Dynamic: description
Dynamic: home-page
Dynamic: license
Dynamic: project-url
Dynamic: provides-extra
Dynamic: requires-dist
Dynamic: requires-python
Dynamic: summary
